testing_hack4u/Roadtrip.py
testing_hack4u/__init__.py
4tlantic-0.1.0.dist-info/METADATA
4tlantic-0.1.0.dist-info/WHEEL
4tlantic-0.1.0.dist-info/top_level.txt
4tlantic-0.1.0.dist-info/RECORD
