Metadata-Version: 2.4
Name: 4tlantic
Version: 0.1.0
Summary: Información sobre algúnas rutas por Galicia
Home-page: https://roadtrip.io
Author: 4tlantic
Dynamic: author
Dynamic: description
Dynamic: description-content-type
Dynamic: home-page
Dynamic: summary
